mydhl/__init__.py
mydhl/api.py
mydhl/config.py
mydhl/cache/__init__.py
mydhl/constants/constants.py
mydhl/endpoints/__init__.py
mydhl/endpoints/base.py
mydhl/endpoints/raterequests.py
mydhl/endpoints/shipmentrequests.py
mydhl/models/__init__.py
mydhl/models/base.py
mydhl/models/general.py
mydhl/models/raterequests.py
mydhl/models/shipmentrequests.py
python_mydhl_api-0.1.0.dist-info/LICENSE.txt
python_mydhl_api-0.1.0.dist-info/METADATA
python_mydhl_api-0.1.0.dist-info/WHEEL
python_mydhl_api-0.1.0.dist-info/top_level.txt
python_mydhl_api-0.1.0.dist-info/RECORD
