Metadata-Version: 2.1
Name: python-mydhl-api
Version: 0.1.0
Summary: Wrapper for the MyDHL API (v2.5)
Home-page: https://github.com/alexanderlhsglobal/python-mydhl-api
Author: Alexander Schillemans
Author-email: alexander.schillemans@lhs.global
License: GPL-3.0-or-later
Keywords: mydhl,api,dhl express,dhl
Platform: UNKNOWN
Classifier: Development Status :: 3 - Alpha
Classifier: Intended Audience :: Developers
Classifier: Topic :: Software Development :: Build Tools
Classifier: License :: OSI Approved :: GNU General Public License v3 or later (GPLv3+)
Classifier: Programming Language :: Python :: 3.6
License-File: LICENSE.txt
Requires-Dist: requests
Requires-Dist: python-dateutil
